{
  "id": "persistence/unit-of-work",
  "title": "Unit of Work",
  "description": "Overview",
  "source": "@site/docs/persistence/unit-of-work.mdx",
  "sourceDirName": "persistence",
  "slug": "/persistence/unit-of-work",
  "permalink": "/docs/next/persistence/unit-of-work",
  "draft": false,
  "unlisted": false,
  "editUrl": "https://github.com/RCommon-Team/RCommon/tree/main/website/docs/persistence/unit-of-work.mdx",
  "tags": [],
  "version": "current",
  "sidebarPosition": 3,
  "frontMatter": {
    "title": "Unit of Work",
    "sidebar_position": 3
  },
  "sidebar": "docsSidebar",
  "previous": {
    "title": "Specifications",
    "permalink": "/docs/next/persistence/specifications"
  },
  "next": {
    "title": "Entity Framework Core",
    "permalink": "/docs/next/persistence/efcore"
  }
}